mess_system_server-0.1.0.data/scripts/server_run
server/__init__.py
server/server_part.py
server/general/__init__.py
server/general/decos.py
server/general/descriptors.py
server/general/errors.py
server/general/metaclasses.py
server/general/utils.py
server/general/variables.py
server/log/__init__.py
server/log/client_log_config.py
server/log/server_log_config.py
server/server/__init__.py
server/server/add_user.py
server/server/config_window.py
server/server/core.py
server/server/database.py
server/server/main_window.py
server/server/remove_user.py
server/server/stat_window.py
mess_system_server-0.1.0.dist-info/METADATA
mess_system_server-0.1.0.dist-info/WHEEL
mess_system_server-0.1.0.dist-info/top_level.txt
mess_system_server-0.1.0.dist-info/RECORD
