Metadata-Version: 2.1
Name: mess-system-server
Version: 0.1.0
Summary: Mess_System Server
Home-page: UNKNOWN
Author: Stasy_Kadr
Author-email: holy_night@mail.ru
License: UNKNOWN
Platform: UNKNOWN
Requires-Dist: PyQt5
Requires-Dist: sqlalchemy
Requires-Dist: pycryptodome
Requires-Dist: pycryptodomex
